{
    "criteria":  {
                     "item0":  {
                                   "trigger":  "minecraft:inventory_changed",
                                   "conditions":  {
                                                      "items":  [
                                                                    {
                                                                        "items":  "angelblock:saltpeter_block"
                                                                    }
                                                                ]
                                                  }
                               },
                     "item1":  {
                                   "trigger":  "minecraft:inventory_changed",
                                   "conditions":  {
                                                      "items":  [
                                                                    {
                                                                        "items":  "angelblock:saltpeter"
                                                                    }
                                                                ]
                                                  }
                               }
                 },
    "parent":  "minecraft:recipes/root",
    "rewards":  {
                    "recipes":  [
                                    "angelblock:saltpeter"
                                ]
                },
    "requirements":  [
                         [
                             "item0",
                             "item1"
                         ]
                     ]
}
